dbapi/DoubanAPI.py
dbapi/Group.py
dbapi/People.py
dbapi/__init__.py
dbapi/base.py
dbapi/cli.py
dbapi/config.py
dbapi/endpoints.py
dbapi/utils.py
dbapi-0.0.14.dist-info/LICENSE
dbapi-0.0.14.dist-info/METADATA
dbapi-0.0.14.dist-info/WHEEL
dbapi-0.0.14.dist-info/entry_points.txt
dbapi-0.0.14.dist-info/top_level.txt
dbapi-0.0.14.dist-info/RECORD
