Metadata-Version: 2.1
Name: dbapi
Version: 0.0.14
Summary: 基于爬虫的豆瓣API SDK
Home-page: https://github.com/acrazing/dbapi
Author: acrazing
Author-email: joking.young@gmail.com
License: MIT
Keywords: 豆瓣 douban 豆瓣小组 api
Platform: UNKNOWN
